download_tools/__init__.py
download_tools/download.py
download_tools/fake_headers/__init__.py
download_tools/fake_headers/browsers.py
download_tools/fake_headers/headers.py
download_tools/fake_headers/platforms.py
download_tools-0.0.4.dist-info/LICENSE
download_tools-0.0.4.dist-info/METADATA
download_tools-0.0.4.dist-info/WHEEL
download_tools-0.0.4.dist-info/top_level.txt
download_tools-0.0.4.dist-info/RECORD
