Metadata-Version: 2.1
Name: download_tools
Version: 0.0.4
Summary: 爬虫的一些工具。
Home-page: https://github.com/ericlib/download_tools
Author: eric
Author-email: ericlib@aliyun.com
Classifier: Programming Language :: Python :: 3
Classifier: License :: OSI Approved :: MIT License
Classifier: Operating System :: OS Independent
Requires-Python: >=3.6
License-File: LICENSE
